{
  "project_info": {
    "project_number": "703645969295",
    "project_id": "serendy-7496b",
    "storage_bucket": "serendy-7496b.appspot.com"
  },
  "client": [
    {
      "client_info": {
        "mobilesdk_app_id": "1:703645969295:android:e057bfe8fd8c5bc707f9fa",
        "android_client_info": {
          "package_name": "com.example.serendy"
        }
      },
      "oauth_client": [
        {
          "client_id": "703645969295-91mv3nht5s0lqc8q1nsjhbsi3a9a65ap.apps.googleusercontent.com",
          "client_type": 3
        }
      ],
      "api_key": [
        {
          "current_key": "AIzaSyD5Jms2G_fKeEK7_6g-a9De7681wa0CivU"
        }
      ],
      "services": {
        "appinvite_service": {
          "other_platform_oauth_client": [
            {
              "client_id": "703645969295-1prj24hgsdu10n56895cp51bsp4u17kh.apps.googleusercontent.com",
              "client_type": 3
            }
          ]
        }
      }
    }
  ],
  "configuration_version": "1"
}